zhdate/__init__.py
zhdate/constants.py
zhdate/model.py
zh_lunar_date-0.0.3.dist-info/LICENSE
zh_lunar_date-0.0.3.dist-info/METADATA
zh_lunar_date-0.0.3.dist-info/WHEEL
zh_lunar_date-0.0.3.dist-info/top_level.txt
zh_lunar_date-0.0.3.dist-info/RECORD
