Metadata-Version: 2.1
Name: zh-lunar-date
Version: 0.0.3
Summary: A pachage to convert Chinese Lunar Calendar to datetime
Home-page: https://github.com/chen-kay/zhdate
Author: Kylin
Author-email: l1328076914@gmail.com
License: UNKNOWN
Platform: UNKNOWN
Classifier: Programming Language :: Python :: 3
Classifier: License :: OSI Approved :: GNU General Public License v3 or later (GPLv3+)
Classifier: Operating System :: OS Independent
